{
    "duplicate_requests": false,
    "exactly_once_output": true,
    "latency (ms)": {
        "10": 1.0,
        "20": 1.0,
        "30": 1.0,
        "40": 1.0,
        "50": 1.0,
        "60": 2.0,
        "70": 2.0,
        "80": 2.0,
        "90": 2.0,
        "95": 3.0,
        "99": 4.0,
        "max": 32.0,
        "min": 1.0,
        "mean": 1.5844801795063574
    },
    "missed messages": 0,
    "throughput": {
        "max": 737,
        "avg": 668.5,
        "TPS": [
            670,
            690,
            692,
            698,
            709,
            691,
            710,
            737,
            653,
            670,
            650,
            640,
            654,
            657,
            689,
            700,
            670,
            673,
            657,
            650,
            650,
            627,
            623,
            680,
            710,
            710,
            690,
            700,
            693,
            677,
            670,
            680,
            690,
            672,
            649,
            669,
            680,
            670,
            700,
            340
        ]
    },
    "duplicate_messages": 0
}